odoo/addons/stock_picking_batch_purchase_price_update/README.rst
odoo/addons/stock_picking_batch_purchase_price_update/__init__.py
odoo/addons/stock_picking_batch_purchase_price_update/__manifest__.py
odoo/addons/stock_picking_batch_purchase_price_update/i18n/stock_picking_batch_purchase_price_update.pot
odoo/addons/stock_picking_batch_purchase_price_update/readme/CONFIGURE.md
odoo/addons/stock_picking_batch_purchase_price_update/readme/CONTRIBUTORS.md
odoo/addons/stock_picking_batch_purchase_price_update/readme/DESCRIPTION.md
odoo/addons/stock_picking_batch_purchase_price_update/readme/USAGE.md
odoo/addons/stock_picking_batch_purchase_price_update/static/description/icon.png
odoo/addons/stock_picking_batch_purchase_price_update/static/description/index.html
odoo/addons/stock_picking_batch_purchase_price_update/views/stock_move_views.xml
odoo_addon_stock_picking_batch_purchase_price_update-15.0.1.0.0.2.dist-info/METADATA
odoo_addon_stock_picking_batch_purchase_price_update-15.0.1.0.0.2.dist-info/WHEEL
odoo_addon_stock_picking_batch_purchase_price_update-15.0.1.0.0.2.dist-info/top_level.txt
odoo_addon_stock_picking_batch_purchase_price_update-15.0.1.0.0.2.dist-info/RECORD
